LICENSE.txt
opendataval/__init__.py
opendataval/__main__.py
opendataval/metrics.py
opendataval/util.py
opendataval/dataloader/__init__.py
opendataval/dataloader/fetcher.py
opendataval/dataloader/noisify.py
opendataval/dataloader/register.py
opendataval/dataloader/util.py
opendataval/dataloader/datasets/__init__.py
opendataval/dataloader/datasets/challenge.py
opendataval/dataloader/datasets/datasets.py
opendataval/dataloader/datasets/imagesets.py
opendataval/dataloader/datasets/nlpsets.py
opendataval/dataval/__init__.py
opendataval/dataval/api.py
opendataval/dataval/ame/__init__.py
opendataval/dataval/ame/ame.py
opendataval/dataval/csshap/__init__.py
opendataval/dataval/csshap/csshap.py
opendataval/dataval/dvrl/__init__.py
opendataval/dataval/dvrl/dvrl.py
opendataval/dataval/influence/__init__.py
opendataval/dataval/influence/influence.py
opendataval/dataval/influence/infsub.py
opendataval/dataval/knnshap/__init__.py
opendataval/dataval/knnshap/knnshap.py
opendataval/dataval/lava/__init__.py
opendataval/dataval/lava/lava.py
opendataval/dataval/lava/otdd.py
opendataval/dataval/margcontrib/__init__.py
opendataval/dataval/margcontrib/banzhaf.py
opendataval/dataval/margcontrib/betashap.py
opendataval/dataval/margcontrib/datashap.py
opendataval/dataval/margcontrib/loo.py
opendataval/dataval/margcontrib/sampler.py
opendataval/dataval/margcontrib/shap.py
opendataval/dataval/oob/__init__.py
opendataval/dataval/oob/oob.py
opendataval/dataval/random/__init__.py
opendataval/dataval/random/random.py
opendataval/dataval/volume/__init__.py
opendataval/dataval/volume/rvs.py
opendataval/experiment/__init__.py
opendataval/experiment/api.py
opendataval/experiment/exper_methods.py
opendataval/experiment/util.py
opendataval/model/__init__.py
opendataval/model/api.py
opendataval/model/bert.py
opendataval/model/grad.py
opendataval/model/lenet.py
opendataval/model/logistic_regression.py
opendataval/model/mlp.py
test/__init__.py
test/test_dataevaluator.py
test/test_dataloader.py
opendataval-1.3.0.dist-info/METADATA
opendataval-1.3.0.dist-info/WHEEL
opendataval-1.3.0.dist-info/entry_points.txt
opendataval-1.3.0.dist-info/licenses/LICENSE.txt
opendataval-1.3.0.dist-info/RECORD
