Metadata-Version: 2.1
Name: opendataval
Version: 1.3.0
Summary: Transparent Data Valuation
Project-URL: Documentation, https://opendataval.github.io
Project-URL: Source code, https://github.com/opendataval/opendataval
Author-email: Kevin Jiang <kfj2112@columbia.edu>, Weixin Liang <wxliang@cs.stanford.edu>, James Zou <jamesz@stanford.edu>, Yongchan Kwon <yk3012@columbia.edu>
License: MIT
License-File: LICENSE.txt
Keywords: Data Centric,Data Valuation,Machine Learning
Classifier: Intended Audience :: Science/Research
Classifier: Programming Language :: Python :: 3
Classifier: Topic :: Scientific/Engineering
Classifier: Topic :: Software Development
Requires-Python: >=3.9.0
Requires-Dist: geomloss~=0.2.6
Requires-Dist: matplotlib~=3.8
Requires-Dist: numpy<1.26,>=1.22.4
Requires-Dist: pandas<2,>=1.5.3
Requires-Dist: pandera~=0.15.1
Requires-Dist: pykeops~=2.1.2
Requires-Dist: requests~=2.31
Requires-Dist: scikit-learn~=1.3
Requires-Dist: scipy~=1.11
Requires-Dist: torcheval~=0.0.7
Requires-Dist: torchvision~=0.16.0
Requires-Dist: torch~=2.1.0
Requires-Dist: tqdm~=4.64.1
Requires-Dist: transformers~=4.35
Requires-Dist: typer~=0.9.0
Provides-Extra: dev
Requires-Dist: black~=23.11.0; extra == 'dev'
Requires-Dist: hatch~=1.7.0; extra == 'dev'
Requires-Dist: pip-tools~=7.3.0; extra == 'dev'
Requires-Dist: pre-commit~=3.5.0; extra == 'dev'
Requires-Dist: ruff~=0.1.5; extra == 'dev'
Requires-Dist: sphinx~=7.2.6; extra == 'dev'
Provides-Extra: test
Requires-Dist: pytest-cov~=4.0.0; extra == 'test'
Requires-Dist: pytest~=7.2.2; extra == 'test'
